bibtex_linter/__init__.py
bibtex_linter/ieeetr_rules.py
bibtex_linter/ieeetran_rules.py
bibtex_linter/main.py
bibtex_linter/parser.py
bibtex_linter/py.typed
bibtex_linter/verification.py
bibtex_linter/version.py
bibtex_linter-2.2.1.dist-info/licenses/LICENSE
bibtex_linter-2.2.1.dist-info/METADATA
bibtex_linter-2.2.1.dist-info/WHEEL
bibtex_linter-2.2.1.dist-info/entry_points.txt
bibtex_linter-2.2.1.dist-info/top_level.txt
bibtex_linter-2.2.1.dist-info/RECORD
