Metadata-Version: 2.4
Name: bibtex_linter
Version: 2.2.1
Summary: A Python tool to parse BibTeX entries and run (custom) checks on them.
Author-email: Sebastian Heppner <mail@s-heppner.com>
License: MIT
Requires-Python: >=3.11
License-File: LICENSE
Provides-Extra: dev
Requires-Dist: mypy; extra == "dev"
Requires-Dist: pycodestyle; extra == "dev"
Requires-Dist: coverage; extra == "dev"
Dynamic: license-file
